{"packages":{"symfony\/symfony":{"3.3.x-dev":{"name":"symfony\/symfony","description":"The Symfony PHP framework","keywords":["framework"],"homepage":"https:\/\/symfony.com","version":"3.3.x-dev","version_normalized":"3.3.9999999.9999999-dev","license":["MIT"],"authors":[{"name":"Fabien Potencier","email":"fabien@symfony.com"},{"name":"Symfony Community","homepage":"https:\/\/symfony.com\/contributors"}],"source":{"type":"git","url":"https:\/\/github.com\/symfony\/symfony.git","reference":"fda994b1e474c821df2433f32f46e23c5b4b393c"},"dist":{"type":"zip","url":"https:\/\/api.github.com\/repos\/symfony\/symfony\/zipball\/fda994b1e474c821df2433f32f46e23c5b4b393c","reference":"fda994b1e474c821df2433f32f46e23c5b4b393c","shasum":""},"type":"library","time":"2017-09-07T07:25:08+00:00","autoload":{"psr-4":{"Symfony\\Bridge\\Doctrine\\":"src\/Symfony\/Bridge\/Doctrine\/","Symfony\\Bridge\\Monolog\\":"src\/Symfony\/Bridge\/Monolog\/","Symfony\\Bridge\\ProxyManager\\":"src\/Symfony\/Bridge\/ProxyManager\/","Symfony\\Bridge\\Twig\\":"src\/Symfony\/Bridge\/Twig\/","Symfony\\Bundle\\":"src\/Symfony\/Bundle\/","Symfony\\Component\\":"src\/Symfony\/Component\/"},"classmap":["src\/Symfony\/Component\/Intl\/Resources\/stubs"],"exclude-from-classmap":["**\/Tests\/"]},"extra":{"branch-alias":{"dev-master":"3.3-dev"}},"require":{"doctrine\/common":"~2.4","ext-xml":"*","fig\/link-util":"^1.0","php":"^5.5.9|>=7.0.8","psr\/cache":"~1.0","psr\/container":"^1.0","psr\/link":"^1.0","psr\/log":"~1.0","psr\/simple-cache":"^1.0","symfony\/polyfill-apcu":"~1.1","symfony\/polyfill-intl-icu":"~1.0","symfony\/polyfill-mbstring":"~1.0","symfony\/polyfill-php56":"~1.0","symfony\/polyfill-php70":"~1.0","symfony\/polyfill-util":"~1.0","twig\/twig":"~1.34|~2.4"},"require-dev":{"cache\/integration-tests":"dev-master","doctrine\/cache":"~1.6","doctrine\/data-fixtures":"1.0.*","doctrine\/dbal":"~2.4","doctrine\/doctrine-bundle":"~1.4","doctrine\/orm":"~2.4,>=2.4.5","egulias\/email-validator":"~1.2,>=1.2.8|~2.0","monolog\/monolog":"~1.11","ocramius\/proxy-manager":"~0.4|~1.0|~2.0","phpdocumentor\/reflection-docblock":"^3.0|^4.0","predis\/predis":"~1.0","sensio\/framework-extra-bundle":"^3.0.2","symfony\/phpunit-bridge":"~3.2","symfony\/security-acl":"~2.8|~3.0"},"conflict":{"phpdocumentor\/type-resolver":"<0.2.0","phpunit\/phpunit":"<4.8.35|<5.4.3,>=5.0","phpdocumentor\/reflection-docblock":"<3.0||>=3.2.0,<3.2.2"},"provide":{"psr\/cache-implementation":"1.0","psr\/container-implementation":"1.0","psr\/simple-cache-implementation":"1.0"},"replace":{"symfony\/asset":"self.version","symfony\/browser-kit":"self.version","symfony\/cache":"self.version","symfony\/class-loader":"self.version","symfony\/config":"self.version","symfony\/console":"self.version","symfony\/css-selector":"self.version","symfony\/dependency-injection":"self.version","symfony\/debug":"self.version","symfony\/debug-bundle":"self.version","symfony\/doctrine-bridge":"self.version","symfony\/dom-crawler":"self.version","symfony\/dotenv":"self.version","symfony\/event-dispatcher":"self.version","symfony\/expression-language":"self.version","symfony\/filesystem":"self.version","symfony\/finder":"self.version","symfony\/form":"self.version","symfony\/framework-bundle":"self.version","symfony\/http-foundation":"self.version","symfony\/http-kernel":"self.version","symfony\/inflector":"self.version","symfony\/intl":"self.version","symfony\/ldap":"self.version","symfony\/monolog-bridge":"self.version","symfony\/options-resolver":"self.version","symfony\/process":"self.version","symfony\/property-access":"self.version","symfony\/property-info":"self.version","symfony\/proxy-manager-bridge":"self.version","symfony\/routing":"self.version","symfony\/security":"self.version","symfony\/security-core":"self.version","symfony\/security-csrf":"self.version","symfony\/security-guard":"self.version","symfony\/security-http":"self.version","symfony\/security-bundle":"self.version","symfony\/serializer":"self.version","symfony\/stopwatch":"self.version","symfony\/templating":"self.version","symfony\/translation":"self.version","symfony\/twig-bridge":"self.version","symfony\/twig-bundle":"self.version","symfony\/validator":"self.version","symfony\/var-dumper":"self.version","symfony\/web-link":"self.version","symfony\/web-profiler-bundle":"self.version","symfony\/web-server-bundle":"self.version","symfony\/workflow":"self.version","symfony\/yaml":"self.version"},"uid":1400251},"3.4.x-dev":{"name":"symfony\/symfony","description":"The Symfony PHP framework","keywords":["framework"],"homepage":"https:\/\/symfony.com","version":"3.4.x-dev","version_normalized":"3.4.9999999.9999999-dev","license":["MIT"],"authors":[{"name":"Fabien Potencier","email":"fabien@symfony.com"},{"name":"Symfony Community","homepage":"https:\/\/symfony.com\/contributors"}],"source":{"type":"git","url":"https:\/\/github.com\/symfony\/symfony.git","reference":"2fde0942ace81ae5f4481cd9a0a7998c42e9f10e"},"dist":{"type":"zip","url":"https:\/\/api.github.com\/repos\/symfony\/symfony\/zipball\/2fde0942ace81ae5f4481cd9a0a7998c42e9f10e","reference":"2fde0942ace81ae5f4481cd9a0a7998c42e9f10e","shasum":""},"type":"library","time":"2017-09-06T21:01:01+00:00","autoload":{"psr-4":{"Symfony\\Bridge\\Doctrine\\":"src\/Symfony\/Bridge\/Doctrine\/","Symfony\\Bridge\\Monolog\\":"src\/Symfony\/Bridge\/Monolog\/","Symfony\\Bridge\\ProxyManager\\":"src\/Symfony\/Bridge\/ProxyManager\/","Symfony\\Bridge\\Twig\\":"src\/Symfony\/Bridge\/Twig\/","Symfony\\Bundle\\":"src\/Symfony\/Bundle\/","Symfony\\Component\\":"src\/Symfony\/Component\/"},"classmap":["src\/Symfony\/Component\/Intl\/Resources\/stubs"],"exclude-from-classmap":["**\/Tests\/"]},"extra":{"branch-alias":{"dev-master":"3.4-dev"}},"require":{"doctrine\/common":"~2.4","ext-xml":"*","fig\/link-util":"^1.0","php":"^5.5.9|>=7.0.8","psr\/cache":"~1.0","psr\/container":"^1.0","psr\/link":"^1.0","psr\/log":"~1.0","psr\/simple-cache":"^1.0","symfony\/polyfill-apcu":"~1.1","symfony\/polyfill-intl-icu":"~1.0","symfony\/polyfill-mbstring":"~1.0","symfony\/polyfill-php56":"~1.0","symfony\/polyfill-php70":"~1.0","symfony\/polyfill-util":"~1.0","twig\/twig":"~1.34|~2.4"},"require-dev":{"cache\/integration-tests":"dev-master","doctrine\/cache":"~1.6","doctrine\/data-fixtures":"1.0.*","doctrine\/dbal":"~2.4","doctrine\/doctrine-bundle":"~1.4","doctrine\/orm":"~2.4,>=2.4.5","egulias\/email-validator":"~1.2,>=1.2.8|~2.0","monolog\/monolog":"~1.11","ocramius\/proxy-manager":"~0.4|~1.0|~2.0","phpdocumentor\/reflection-docblock":"^3.0|^4.0","predis\/predis":"~1.0","symfony\/phpunit-bridge":"~3.2","symfony\/security-acl":"~2.8|~3.0"},"conflict":{"phpdocumentor\/type-resolver":"<0.2.0","phpunit\/phpunit":"<4.8.35|<5.4.3,>=5.0","phpdocumentor\/reflection-docblock":"<3.0||>=3.2.0,<3.2.2"},"provide":{"psr\/cache-implementation":"1.0","psr\/container-implementation":"1.0","psr\/simple-cache-implementation":"1.0"},"replace":{"symfony\/asset":"self.version","symfony\/browser-kit":"self.version","symfony\/cache":"self.version","symfony\/class-loader":"self.version","symfony\/config":"self.version","symfony\/console":"self.version","symfony\/css-selector":"self.version","symfony\/dependency-injection":"self.version","symfony\/debug":"self.version","symfony\/debug-bundle":"self.version","symfony\/doctrine-bridge":"self.version","symfony\/dom-crawler":"self.version","symfony\/dotenv":"self.version","symfony\/event-dispatcher":"self.version","symfony\/expression-language":"self.version","symfony\/filesystem":"self.version","symfony\/finder":"self.version","symfony\/form":"self.version","symfony\/framework-bundle":"self.version","symfony\/http-foundation":"self.version","symfony\/http-kernel":"self.version","symfony\/inflector":"self.version","symfony\/intl":"self.version","symfony\/ldap":"self.version","symfony\/monolog-bridge":"self.version","symfony\/options-resolver":"self.version","symfony\/process":"self.version","symfony\/property-access":"self.version","symfony\/property-info":"self.version","symfony\/proxy-manager-bridge":"self.version","symfony\/routing":"self.version","symfony\/security":"self.version","symfony\/security-core":"self.version","symfony\/security-csrf":"self.version","symfony\/security-guard":"self.version","symfony\/security-http":"self.version","symfony\/security-bundle":"self.version","symfony\/serializer":"self.version","symfony\/stopwatch":"self.version","symfony\/templating":"self.version","symfony\/translation":"self.version","symfony\/twig-bridge":"self.version","symfony\/twig-bundle":"self.version","symfony\/validator":"self.version","symfony\/var-dumper":"self.version","symfony\/web-link":"self.version","symfony\/web-profiler-bundle":"self.version","symfony\/web-server-bundle":"self.version","symfony\/workflow":"self.version","symfony\/yaml":"self.version","symfony\/lock":"self.version"},"uid":1400264},"dev-master":{"name":"symfony\/symfony","description":"The Symfony PHP framework","keywords":["framework"],"homepage":"https:\/\/symfony.com","version":"dev-master","version_normalized":"9999999-dev","license":["MIT"],"authors":[{"name":"Fabien Potencier","email":"fabien@symfony.com"},{"name":"Symfony Community","homepage":"https:\/\/symfony.com\/contributors"}],"source":{"type":"git","url":"https:\/\/github.com\/symfony\/symfony.git","reference":"1dfdc628b085543e8a4c5cb829202df99ab4b994"},"dist":{"type":"zip","url":"https:\/\/api.github.com\/repos\/symfony\/symfony\/zipball\/1dfdc628b085543e8a4c5cb829202df99ab4b994","reference":"1dfdc628b085543e8a4c5cb829202df99ab4b994","shasum":""},"type":"library","time":"2017-09-06T21:01:33+00:00","autoload":{"psr-4":{"Symfony\\Bridge\\Doctrine\\":"src\/Symfony\/Bridge\/Doctrine\/","Symfony\\Bridge\\Monolog\\":"src\/Symfony\/Bridge\/Monolog\/","Symfony\\Bridge\\ProxyManager\\":"src\/Symfony\/Bridge\/ProxyManager\/","Symfony\\Bridge\\Twig\\":"src\/Symfony\/Bridge\/Twig\/","Symfony\\Bundle\\":"src\/Symfony\/Bundle\/","Symfony\\Component\\":"src\/Symfony\/Component\/"},"classmap":["src\/Symfony\/Component\/Intl\/Resources\/stubs"],"exclude-from-classmap":["**\/Tests\/"]},"extra":{"branch-alias":{"dev-master":"4.0-dev"}},"require":{"doctrine\/common":"~2.4","ext-xml":"*","fig\/link-util":"^1.0","php":"^7.1.3","psr\/cache":"~1.0","psr\/container":"^1.0","psr\/link":"^1.0","psr\/log":"~1.0","psr\/simple-cache":"^1.0","symfony\/polyfill-intl-icu":"~1.0","symfony\/polyfill-mbstring":"~1.0","symfony\/polyfill-php72":"~1.5","twig\/twig":"~1.34|~2.4"},"require-dev":{"cache\/integration-tests":"dev-master","doctrine\/cache":"~1.6","doctrine\/data-fixtures":"1.0.*","doctrine\/dbal":"~2.4","doctrine\/doctrine-bundle":"~1.4","doctrine\/orm":"~2.4,>=2.4.5","egulias\/email-validator":"~1.2,>=1.2.8|~2.0","monolog\/monolog":"~1.11","ocramius\/proxy-manager":"~0.4|~1.0|~2.0","phpdocumentor\/reflection-docblock":"^3.0|^4.0","predis\/predis":"~1.0","symfony\/phpunit-bridge":"~3.2","symfony\/security-acl":"~2.8|~3.0"},"conflict":{"phpdocumentor\/type-resolver":"<0.2.0","phpunit\/phpunit":"<4.8.35|<5.4.3,>=5.0","phpdocumentor\/reflection-docblock":"<3.0||>=3.2.0,<3.2.2"},"provide":{"psr\/cache-implementation":"1.0","psr\/simple-cache-implementation":"1.0","psr\/container-implementation":"1.0"},"replace":{"symfony\/asset":"self.version","symfony\/browser-kit":"self.version","symfony\/cache":"self.version","symfony\/config":"self.version","symfony\/console":"self.version","symfony\/css-selector":"self.version","symfony\/dependency-injection":"self.version","symfony\/debug":"self.version","symfony\/debug-bundle":"self.version","symfony\/doctrine-bridge":"self.version","symfony\/dom-crawler":"self.version","symfony\/event-dispatcher":"self.version","symfony\/expression-language":"self.version","symfony\/filesystem":"self.version","symfony\/finder":"self.version","symfony\/form":"self.version","symfony\/framework-bundle":"self.version","symfony\/http-foundation":"self.version","symfony\/http-kernel":"self.version","symfony\/intl":"self.version","symfony\/ldap":"self.version","symfony\/monolog-bridge":"self.version","symfony\/options-resolver":"self.version","symfony\/process":"self.version","symfony\/property-access":"self.version","symfony\/property-info":"self.version","symfony\/proxy-manager-bridge":"self.version","symfony\/routing":"self.version","symfony\/security":"self.version","symfony\/security-core":"self.version","symfony\/security-csrf":"self.version","symfony\/security-guard":"self.version","symfony\/security-http":"self.version","symfony\/security-bundle":"self.version","symfony\/serializer":"self.version","symfony\/stopwatch":"self.version","symfony\/templating":"self.version","symfony\/translation":"self.version","symfony\/twig-bridge":"self.version","symfony\/twig-bundle":"self.version","symfony\/validator":"self.version","symfony\/var-dumper":"self.version","symfony\/web-profiler-bundle":"self.version","symfony\/yaml":"self.version","symfony\/workflow":"self.version","symfony\/inflector":"self.version","symfony\/web-server-bundle":"self.version","symfony\/dotenv":"self.version","symfony\/web-link":"self.version","symfony\/lock":"self.version"},"uid":664487},"v3.3.0":{"name":"symfony\/symfony","description":"The Symfony PHP framework","keywords":["framework"],"homepage":"https:\/\/symfony.com","version":"v3.3.0","version_normalized":"3.3.0.0","license":["MIT"],"authors":[{"name":"Fabien Potencier","email":"fabien@symfony.com"},{"name":"Symfony Community","homepage":"https:\/\/symfony.com\/contributors"}],"source":{"type":"git","url":"https:\/\/github.com\/symfony\/symfony.git","reference":"5a7e31c48e7cd4831efa409fffb661beb9995174"},"dist":{"type":"zip","url":"https:\/\/api.github.com\/repos\/symfony\/symfony\/zipball\/5a7e31c48e7cd4831efa409fffb661beb9995174","reference":"5a7e31c48e7cd4831efa409fffb661beb9995174","shasum":""},"type":"library","time":"2017-05-29T21:02:32+00:00","autoload":{"psr-4":{"Symfony\\Bridge\\Doctrine\\":"src\/Symfony\/Bridge\/Doctrine\/","Symfony\\Bridge\\Monolog\\":"src\/Symfony\/Bridge\/Monolog\/","Symfony\\Bridge\\ProxyManager\\":"src\/Symfony\/Bridge\/ProxyManager\/","Symfony\\Bridge\\Swiftmailer\\":"src\/Symfony\/Bridge\/Swiftmailer\/","Symfony\\Bridge\\Twig\\":"src\/Symfony\/Bridge\/Twig\/","Symfony\\Bundle\\":"src\/Symfony\/Bundle\/","Symfony\\Component\\":"src\/Symfony\/Component\/"},"classmap":["src\/Symfony\/Component\/Intl\/Resources\/stubs"],"exclude-from-classmap":["**\/Tests\/"]},"extra":{"branch-alias":{"dev-master":"3.3-dev"}},"require":{"doctrine\/common":"~2.4","fig\/link-util":"^1.0","php":">=5.5.9","psr\/cache":"~1.0","psr\/container":"^1.0","psr\/link":"^1.0","psr\/log":"~1.0","psr\/simple-cache":"^1.0","symfony\/polyfill-intl-icu":"~1.0","symfony\/polyfill-mbstring":"~1.0","symfony\/polyfill-php56":"~1.0","symfony\/polyfill-php70":"~1.0","symfony\/polyfill-util":"~1.0","twig\/twig":"~1.32|~2.2"},"require-dev":{"cache\/integration-tests":"dev-master","doctrine\/cache":"~1.6","doctrine\/data-fixtures":"1.0.*","doctrine\/dbal":"~2.4","doctrine\/doctrine-bundle":"~1.4","doctrine\/orm":"~2.4,>=2.4.5","egulias\/email-validator":"~1.2,>=1.2.8|~2.0","monolog\/monolog":"~1.11","ocramius\/proxy-manager":"~0.4|~1.0|~2.0","phpdocumentor\/reflection-docblock":"^3.0","predis\/predis":"~1.0","sensio\/framework-extra-bundle":"^3.0.2","symfony\/phpunit-bridge":"~3.2","symfony\/polyfill-apcu":"~1.1","symfony\/security-acl":"~2.8|~3.0"},"conflict":{"phpdocumentor\/reflection-docblock":"<3.0","phpdocumentor\/type-resolver":"<0.2.0","phpunit\/phpunit":"<4.8.35|<5.4.3,>=5.0"},"provide":{"psr\/cache-implementation":"1.0","psr\/container-implementation":"1.0","psr\/simple-cache-implementation":"1.0"},"replace":{"symfony\/asset":"self.version","symfony\/browser-kit":"self.version","symfony\/cache":"self.version","symfony\/class-loader":"self.version","symfony\/config":"self.version","symfony\/console":"self.version","symfony\/css-selector":"self.version","symfony\/dependency-injection":"self.version","symfony\/debug":"self.version","symfony\/debug-bundle":"self.version","symfony\/doctrine-bridge":"self.version","symfony\/dom-crawler":"self.version","symfony\/dotenv":"self.version","symfony\/event-dispatcher":"self.version","symfony\/expression-language":"self.version","symfony\/filesystem":"self.version","symfony\/finder":"self.version","symfony\/form":"self.version","symfony\/framework-bundle":"self.version","symfony\/http-foundation":"self.version","symfony\/http-kernel":"self.version","symfony\/inflector":"self.version","symfony\/intl":"self.version","symfony\/ldap":"self.version","symfony\/monolog-bridge":"self.version","symfony\/options-resolver":"self.version","symfony\/process":"self.version","symfony\/property-access":"self.version","symfony\/property-info":"self.version","symfony\/proxy-manager-bridge":"self.version","symfony\/routing":"self.version","symfony\/security":"self.version","symfony\/security-core":"self.version","symfony\/security-csrf":"self.version","symfony\/security-guard":"self.version","symfony\/security-http":"self.version","symfony\/security-bundle":"self.version","symfony\/serializer":"self.version","symfony\/stopwatch":"self.version","symfony\/templating":"self.version","symfony\/translation":"self.version","symfony\/twig-bridge":"self.version","symfony\/twig-bundle":"self.version","symfony\/validator":"self.version","symfony\/var-dumper":"self.version","symfony\/web-link":"self.version","symfony\/web-profiler-bundle":"self.version","symfony\/web-server-bundle":"self.version","symfony\/workflow":"self.version","symfony\/yaml":"self.version"},"uid":1417864},"v3.3.0-BETA1":{"name":"symfony\/symfony","description":"The Symfony PHP framework","keywords":["framework"],"homepage":"https:\/\/symfony.com","version":"v3.3.0-BETA1","version_normalized":"3.3.0.0-beta1","license":["MIT"],"authors":[{"name":"Fabien Potencier","email":"fabien@symfony.com"},{"name":"Symfony Community","homepage":"https:\/\/symfony.com\/contributors"}],"source":{"type":"git","url":"https:\/\/github.com\/symfony\/symfony.git","reference":"0fa394005cd49e0001b3b095ecdaf3a35a5eca27"},"dist":{"type":"zip","url":"https:\/\/api.github.com\/repos\/symfony\/symfony\/zipball\/0fa394005cd49e0001b3b095ecdaf3a35a5eca27","reference":"0fa394005cd49e0001b3b095ecdaf3a35a5eca27","shasum":""},"type":"library","time":"2017-05-01T18:30:51+00:00","autoload":{"psr-4":{"Symfony\\Bridge\\Doctrine\\":"src\/Symfony\/Bridge\/Doctrine\/","Symfony\\Bridge\\Monolog\\":"src\/Symfony\/Bridge\/Monolog\/","Symfony\\Bridge\\ProxyManager\\":"src\/Symfony\/Bridge\/ProxyManager\/","Symfony\\Bridge\\Swiftmailer\\":"src\/Symfony\/Bridge\/Swiftmailer\/","Symfony\\Bridge\\Twig\\":"src\/Symfony\/Bridge\/Twig\/","Symfony\\Bundle\\":"src\/Symfony\/Bundle\/","Symfony\\Component\\":"src\/Symfony\/Component\/"},"classmap":["src\/Symfony\/Component\/Intl\/Resources\/stubs"],"exclude-from-classmap":["**\/Tests\/"]},"extra":{"branch-alias":{"dev-master":"3.3-dev"}},"require":{"doctrine\/common":"~2.4","fig\/link-util":"^1.0","php":">=5.5.9","psr\/cache":"~1.0","psr\/container":"^1.0","psr\/link":"^1.0","psr\/log":"~1.0","psr\/simple-cache":"^1.0","symfony\/polyfill-intl-icu":"~1.0","symfony\/polyfill-mbstring":"~1.0","symfony\/polyfill-php56":"~1.0","symfony\/polyfill-php70":"~1.0","symfony\/polyfill-util":"~1.0","twig\/twig":"~1.32|~2.2"},"require-dev":{"cache\/integration-tests":"dev-master","doctrine\/cache":"~1.6","doctrine\/data-fixtures":"1.0.*","doctrine\/dbal":"~2.4","doctrine\/doctrine-bundle":"~1.4","doctrine\/orm":"~2.4,>=2.4.5","egulias\/email-validator":"~1.2,>=1.2.8|~2.0","monolog\/monolog":"~1.11","ocramius\/proxy-manager":"~0.4|~1.0|~2.0","phpdocumentor\/reflection-docblock":"^3.0","predis\/predis":"~1.0","sensio\/framework-extra-bundle":"^3.0.2","symfony\/phpunit-bridge":"~3.2","symfony\/polyfill-apcu":"~1.1","symfony\/security-acl":"~2.8|~3.0"},"conflict":{"phpdocumentor\/reflection-docblock":"<3.0","phpdocumentor\/type-resolver":"<0.2.0","phpunit\/phpunit":"<4.8.35|<5.4.3,>=5.0"},"provide":{"psr\/cache-implementation":"1.0","psr\/container-implementation":"1.0","psr\/simple-cache-implementation":"1.0"},"replace":{"symfony\/asset":"self.version","symfony\/browser-kit":"self.version","symfony\/cache":"self.version","symfony\/class-loader":"self.version","symfony\/config":"self.version","symfony\/console":"self.version","symfony\/css-selector":"self.version","symfony\/dependency-injection":"self.version","symfony\/debug":"self.version","symfony\/debug-bundle":"self.version","symfony\/doctrine-bridge":"self.version","symfony\/dom-crawler":"self.version","symfony\/dotenv":"self.version","symfony\/event-dispatcher":"self.version","symfony\/expression-language":"self.version","symfony\/filesystem":"self.version","symfony\/finder":"self.version","symfony\/form":"self.version","symfony\/framework-bundle":"self.version","symfony\/http-foundation":"self.version","symfony\/http-kernel":"self.version","symfony\/inflector":"self.version","symfony\/intl":"self.version","symfony\/ldap":"self.version","symfony\/monolog-bridge":"self.version","symfony\/options-resolver":"self.version","symfony\/process":"self.version","symfony\/property-access":"self.version","symfony\/property-info":"self.version","symfony\/proxy-manager-bridge":"self.version","symfony\/routing":"self.version","symfony\/security":"self.version","symfony\/security-core":"self.version","symfony\/security-csrf":"self.version","symfony\/security-guard":"self.version","symfony\/security-http":"self.version","symfony\/security-bundle":"self.version","symfony\/serializer":"self.version","symfony\/stopwatch":"self.version","symfony\/templating":"self.version","symfony\/translation":"self.version","symfony\/twig-bridge":"self.version","symfony\/twig-bundle":"self.version","symfony\/validator":"self.version","symfony\/var-dumper":"self.version","symfony\/web-link":"self.version","symfony\/web-profiler-bundle":"self.version","symfony\/web-server-bundle":"self.version","symfony\/workflow":"self.version","symfony\/yaml":"self.version"},"uid":1369930},"v3.3.0-RC1":{"name":"symfony\/symfony","description":"The Symfony PHP framework","keywords":["framework"],"homepage":"https:\/\/symfony.com","version":"v3.3.0-RC1","version_normalized":"3.3.0.0-RC1","license":["MIT"],"authors":[{"name":"Fabien Potencier","email":"fabien@symfony.com"},{"name":"Symfony Community","homepage":"https:\/\/symfony.com\/contributors"}],"source":{"type":"git","url":"https:\/\/github.com\/symfony\/symfony.git","reference":"a66d56bfde7edd0f3b9e2857131561348234832b"},"dist":{"type":"zip","url":"https:\/\/api.github.com\/repos\/symfony\/symfony\/zipball\/a66d56bfde7edd0f3b9e2857131561348234832b","reference":"a66d56bfde7edd0f3b9e2857131561348234832b","shasum":""},"type":"library","time":"2017-05-17T18:10:19+00:00","autoload":{"psr-4":{"Symfony\\Bridge\\Doctrine\\":"src\/Symfony\/Bridge\/Doctrine\/","Symfony\\Bridge\\Monolog\\":"src\/Symfony\/Bridge\/Monolog\/","Symfony\\Bridge\\ProxyManager\\":"src\/Symfony\/Bridge\/ProxyManager\/","Symfony\\Bridge\\Swiftmailer\\":"src\/Symfony\/Bridge\/Swiftmailer\/","Symfony\\Bridge\\Twig\\":"src\/Symfony\/Bridge\/Twig\/","Symfony\\Bundle\\":"src\/Symfony\/Bundle\/","Symfony\\Component\\":"src\/Symfony\/Component\/"},"classmap":["src\/Symfony\/Component\/Intl\/Resources\/stubs"],"exclude-from-classmap":["**\/Tests\/"]},"extra":{"branch-alias":{"dev-master":"3.3-dev"}},"require":{"doctrine\/common":"~2.4","fig\/link-util":"^1.0","php":">=5.5.9","psr\/cache":"~1.0","psr\/container":"^1.0","psr\/link":"^1.0","psr\/log":"~1.0","psr\/simple-cache":"^1.0","symfony\/polyfill-intl-icu":"~1.0","symfony\/polyfill-mbstring":"~1.0","symfony\/polyfill-php56":"~1.0","symfony\/polyfill-php70":"~1.0","symfony\/polyfill-util":"~1.0","twig\/twig":"~1.32|~2.2"},"require-dev":{"cache\/integration-tests":"dev-master","doctrine\/cache":"~1.6","doctrine\/data-fixtures":"1.0.*","doctrine\/dbal":"~2.4","doctrine\/doctrine-bundle":"~1.4","doctrine\/orm":"~2.4,>=2.4.5","egulias\/email-validator":"~1.2,>=1.2.8|~2.0","monolog\/monolog":"~1.11","ocramius\/proxy-manager":"~0.4|~1.0|~2.0","phpdocumentor\/reflection-docblock":"^3.0","predis\/predis":"~1.0","sensio\/framework-extra-bundle":"^3.0.2","symfony\/phpunit-bridge":"~3.2","symfony\/polyfill-apcu":"~1.1","symfony\/security-acl":"~2.8|~3.0"},"conflict":{"phpdocumentor\/reflection-docblock":"<3.0","phpdocumentor\/type-resolver":"<0.2.0","phpunit\/phpunit":"<4.8.35|<5.4.3,>=5.0"},"provide":{"psr\/cache-implementation":"1.0","psr\/container-implementation":"1.0","psr\/simple-cache-implementation":"1.0"},"replace":{"symfony\/asset":"self.version","symfony\/browser-kit":"self.version","symfony\/cache":"self.version","symfony\/class-loader":"self.version","symfony\/config":"self.version","symfony\/console":"self.version","symfony\/css-selector":"self.version","symfony\/dependency-injection":"self.version","symfony\/debug":"self.version","symfony\/debug-bundle":"self.version","symfony\/doctrine-bridge":"self.version","symfony\/dom-crawler":"self.version","symfony\/dotenv":"self.version","symfony\/event-dispatcher":"self.version","symfony\/expression-language":"self.version","symfony\/filesystem":"self.version","symfony\/finder":"self.version","symfony\/form":"self.version","symfony\/framework-bundle":"self.version","symfony\/http-foundation":"self.version","symfony\/http-kernel":"self.version","symfony\/inflector":"self.version","symfony\/intl":"self.version","symfony\/ldap":"self.version","symfony\/monolog-bridge":"self.version","symfony\/options-resolver":"self.version","symfony\/process":"self.version","symfony\/property-access":"self.version","symfony\/property-info":"self.version","symfony\/proxy-manager-bridge":"self.version","symfony\/routing":"self.version","symfony\/security":"self.version","symfony\/security-core":"self.version","symfony\/security-csrf":"self.version","symfony\/security-guard":"self.version","symfony\/security-http":"self.version","symfony\/security-bundle":"self.version","symfony\/serializer":"self.version","symfony\/stopwatch":"self.version","symfony\/templating":"self.version","symfony\/translation":"self.version","symfony\/twig-bridge":"self.version","symfony\/twig-bundle":"self.version","symfony\/validator":"self.version","symfony\/var-dumper":"self.version","symfony\/web-link":"self.version","symfony\/web-profiler-bundle":"self.version","symfony\/web-server-bundle":"self.version","symfony\/workflow":"self.version","symfony\/yaml":"self.version"},"uid":1400476},"v3.3.1":{"name":"symfony\/symfony","description":"The Symfony PHP framework","keywords":["framework"],"homepage":"https:\/\/symfony.com","version":"v3.3.1","version_normalized":"3.3.1.0","license":["MIT"],"authors":[{"name":"Fabien Potencier","email":"fabien@symfony.com"},{"name":"Symfony Community","homepage":"https:\/\/symfony.com\/contributors"}],"source":{"type":"git","url":"https:\/\/github.com\/symfony\/symfony.git","reference":"de4db89980282f960211efd029bb6ca754999dbd"},"dist":{"type":"zip","url":"https:\/\/api.github.com\/repos\/symfony\/symfony\/zipball\/de4db89980282f960211efd029bb6ca754999dbd","reference":"de4db89980282f960211efd029bb6ca754999dbd","shasum":""},"type":"library","time":"2017-06-05T17:32:18+00:00","autoload":{"psr-4":{"Symfony\\Bridge\\Doctrine\\":"src\/Symfony\/Bridge\/Doctrine\/","Symfony\\Bridge\\Monolog\\":"src\/Symfony\/Bridge\/Monolog\/","Symfony\\Bridge\\ProxyManager\\":"src\/Symfony\/Bridge\/ProxyManager\/","Symfony\\Bridge\\Swiftmailer\\":"src\/Symfony\/Bridge\/Swiftmailer\/","Symfony\\Bridge\\Twig\\":"src\/Symfony\/Bridge\/Twig\/","Symfony\\Bundle\\":"src\/Symfony\/Bundle\/","Symfony\\Component\\":"src\/Symfony\/Component\/"},"classmap":["src\/Symfony\/Component\/Intl\/Resources\/stubs"],"exclude-from-classmap":["**\/Tests\/"]},"extra":{"branch-alias":{"dev-master":"3.3-dev"}},"require":{"doctrine\/common":"~2.4","fig\/link-util":"^1.0","php":">=5.5.9","psr\/cache":"~1.0","psr\/container":"^1.0","psr\/link":"^1.0","psr\/log":"~1.0","psr\/simple-cache":"^1.0","symfony\/polyfill-intl-icu":"~1.0","symfony\/polyfill-mbstring":"~1.0","symfony\/polyfill-php56":"~1.0","symfony\/polyfill-php70":"~1.0","symfony\/polyfill-util":"~1.0","twig\/twig":"~1.34|~2.4"},"require-dev":{"cache\/integration-tests":"dev-master","doctrine\/cache":"~1.6","doctrine\/data-fixtures":"1.0.*","doctrine\/dbal":"~2.4","doctrine\/doctrine-bundle":"~1.4","doctrine\/orm":"~2.4,>=2.4.5","egulias\/email-validator":"~1.2,>=1.2.8|~2.0","monolog\/monolog":"~1.11","ocramius\/proxy-manager":"~0.4|~1.0|~2.0","phpdocumentor\/reflection-docblock":"^3.0","predis\/predis":"~1.0","sensio\/framework-extra-bundle":"^3.0.2","symfony\/phpunit-bridge":"~3.2","symfony\/polyfill-apcu":"~1.1","symfony\/security-acl":"~2.8|~3.0"},"conflict":{"phpdocumentor\/reflection-docblock":"<3.0","phpdocumentor\/type-resolver":"<0.2.0","phpunit\/phpunit":"<4.8.35|<5.4.3,>=5.0"},"provide":{"psr\/cache-implementation":"1.0","psr\/container-implementation":"1.0","psr\/simple-cache-implementation":"1.0"},"replace":{"symfony\/asset":"self.version","symfony\/browser-kit":"self.version","symfony\/cache":"self.version","symfony\/class-loader":"self.version","symfony\/config":"self.version","symfony\/console":"self.version","symfony\/css-selector":"self.version","symfony\/dependency-injection":"self.version","symfony\/debug":"self.version","symfony\/debug-bundle":"self.version","symfony\/doctrine-bridge":"self.version","symfony\/dom-crawler":"self.version","symfony\/dotenv":"self.version","symfony\/event-dispatcher":"self.version","symfony\/expression-language":"self.version","symfony\/filesystem":"self.version","symfony\/finder":"self.version","symfony\/form":"self.version","symfony\/framework-bundle":"self.version","symfony\/http-foundation":"self.version","symfony\/http-kernel":"self.version","symfony\/inflector":"self.version","symfony\/intl":"self.version","symfony\/ldap":"self.version","symfony\/monolog-bridge":"self.version","symfony\/options-resolver":"self.version","symfony\/process":"self.version","symfony\/property-access":"self.version","symfony\/property-info":"self.version","symfony\/proxy-manager-bridge":"self.version","symfony\/routing":"self.version","symfony\/security":"self.version","symfony\/security-core":"self.version","symfony\/security-csrf":"self.version","symfony\/security-guard":"self.version","symfony\/security-http":"self.version","symfony\/security-bundle":"self.version","symfony\/serializer":"self.version","symfony\/stopwatch":"self.version","symfony\/templating":"self.version","symfony\/translation":"self.version","symfony\/twig-bridge":"self.version","symfony\/twig-bundle":"self.version","symfony\/validator":"self.version","symfony\/var-dumper":"self.version","symfony\/web-link":"self.version","symfony\/web-profiler-bundle":"self.version","symfony\/web-server-bundle":"self.version","symfony\/workflow":"self.version","symfony\/yaml":"self.version"},"uid":1428898},"v3.3.2":{"name":"symfony\/symfony","description":"The Symfony PHP framework","keywords":["framework"],"homepage":"https:\/\/symfony.com","version":"v3.3.2","version_normalized":"3.3.2.0","license":["MIT"],"authors":[{"name":"Fabien Potencier","email":"fabien@symfony.com"},{"name":"Symfony Community","homepage":"https:\/\/symfony.com\/contributors"}],"source":{"type":"git","url":"https:\/\/github.com\/symfony\/symfony.git","reference":"82bd7c039214b34bb5d12c04f996f05f6581c49f"},"dist":{"type":"zip","url":"https:\/\/api.github.com\/repos\/symfony\/symfony\/zipball\/82bd7c039214b34bb5d12c04f996f05f6581c49f","reference":"82bd7c039214b34bb5d12c04f996f05f6581c49f","shasum":""},"type":"library","time":"2017-06-06T04:00:14+00:00","autoload":{"psr-4":{"Symfony\\Bridge\\Doctrine\\":"src\/Symfony\/Bridge\/Doctrine\/","Symfony\\Bridge\\Monolog\\":"src\/Symfony\/Bridge\/Monolog\/","Symfony\\Bridge\\ProxyManager\\":"src\/Symfony\/Bridge\/ProxyManager\/","Symfony\\Bridge\\Swiftmailer\\":"src\/Symfony\/Bridge\/Swiftmailer\/","Symfony\\Bridge\\Twig\\":"src\/Symfony\/Bridge\/Twig\/","Symfony\\Bundle\\":"src\/Symfony\/Bundle\/","Symfony\\Component\\":"src\/Symfony\/Component\/"},"classmap":["src\/Symfony\/Component\/Intl\/Resources\/stubs"],"exclude-from-classmap":["**\/Tests\/"]},"extra":{"branch-alias":{"dev-master":"3.3-dev"}},"require":{"doctrine\/common":"~2.4","fig\/link-util":"^1.0","php":">=5.5.9","psr\/cache":"~1.0","psr\/container":"^1.0","psr\/link":"^1.0","psr\/log":"~1.0","psr\/simple-cache":"^1.0","symfony\/polyfill-intl-icu":"~1.0","symfony\/polyfill-mbstring":"~1.0","symfony\/polyfill-php56":"~1.0","symfony\/polyfill-php70":"~1.0","symfony\/polyfill-util":"~1.0","twig\/twig":"~1.34|~2.4"},"require-dev":{"cache\/integration-tests":"dev-master","doctrine\/cache":"~1.6","doctrine\/data-fixtures":"1.0.*","doctrine\/dbal":"~2.4","doctrine\/doctrine-bundle":"~1.4","doctrine\/orm":"~2.4,>=2.4.5","egulias\/email-validator":"~1.2,>=1.2.8|~2.0","monolog\/monolog":"~1.11","ocramius\/proxy-manager":"~0.4|~1.0|~2.0","phpdocumentor\/reflection-docblock":"^3.0","predis\/predis":"~1.0","sensio\/framework-extra-bundle":"^3.0.2","symfony\/phpunit-bridge":"~3.2","symfony\/polyfill-apcu":"~1.1","symfony\/security-acl":"~2.8|~3.0"},"conflict":{"phpdocumentor\/reflection-docblock":"<3.0","phpdocumentor\/type-resolver":"<0.2.0","phpunit\/phpunit":"<4.8.35|<5.4.3,>=5.0"},"provide":{"psr\/cache-implementation":"1.0","psr\/container-implementation":"1.0","psr\/simple-cache-implementation":"1.0"},"replace":{"symfony\/asset":"self.version","symfony\/browser-kit":"self.version","symfony\/cache":"self.version","symfony\/class-loader":"self.version","symfony\/config":"self.version","symfony\/console":"self.version","symfony\/css-selector":"self.version","symfony\/dependency-injection":"self.version","symfony\/debug":"self.version","symfony\/debug-bundle":"self.version","symfony\/doctrine-bridge":"self.version","symfony\/dom-crawler":"self.version","symfony\/dotenv":"self.version","symfony\/event-dispatcher":"self.version","symfony\/expression-language":"self.version","symfony\/filesystem":"self.version","symfony\/finder":"self.version","symfony\/form":"self.version","symfony\/framework-bundle":"self.version","symfony\/http-foundation":"self.version","symfony\/http-kernel":"self.version","symfony\/inflector":"self.version","symfony\/intl":"self.version","symfony\/ldap":"self.version","symfony\/monolog-bridge":"self.version","symfony\/options-resolver":"self.version","symfony\/process":"self.version","symfony\/property-access":"self.version","symfony\/property-info":"self.version","symfony\/proxy-manager-bridge":"self.version","symfony\/routing":"self.version","symfony\/security":"self.version","symfony\/security-core":"self.version","symfony\/security-csrf":"self.version","symfony\/security-guard":"self.version","symfony\/security-http":"self.version","symfony\/security-bundle":"self.version","symfony\/serializer":"self.version","symfony\/stopwatch":"self.version","symfony\/templating":"self.version","symfony\/translation":"self.version","symfony\/twig-bridge":"self.version","symfony\/twig-bundle":"self.version","symfony\/validator":"self.version","symfony\/var-dumper":"self.version","symfony\/web-link":"self.version","symfony\/web-profiler-bundle":"self.version","symfony\/web-server-bundle":"self.version","symfony\/workflow":"self.version","symfony\/yaml":"self.version"},"uid":1429567},"v3.3.3":{"name":"symfony\/symfony","description":"The Symfony PHP framework","keywords":["framework"],"homepage":"https:\/\/symfony.com","version":"v3.3.3","version_normalized":"3.3.3.0","license":["MIT"],"authors":[{"name":"Fabien Potencier","email":"fabien@symfony.com"},{"name":"Symfony Community","homepage":"https:\/\/symfony.com\/contributors"}],"source":{"type":"git","url":"https:\/\/github.com\/symfony\/symfony.git","reference":"098bb166d51cdf0b0541550d037bb3ad1f8fa846"},"dist":{"type":"zip","url":"https:\/\/api.github.com\/repos\/symfony\/symfony\/zipball\/098bb166d51cdf0b0541550d037bb3ad1f8fa846","reference":"098bb166d51cdf0b0541550d037bb3ad1f8fa846","shasum":""},"type":"library","time":"2017-07-04T06:03:16+00:00","autoload":{"psr-4":{"Symfony\\Bridge\\Doctrine\\":"src\/Symfony\/Bridge\/Doctrine\/","Symfony\\Bridge\\Monolog\\":"src\/Symfony\/Bridge\/Monolog\/","Symfony\\Bridge\\ProxyManager\\":"src\/Symfony\/Bridge\/ProxyManager\/","Symfony\\Bridge\\Twig\\":"src\/Symfony\/Bridge\/Twig\/","Symfony\\Bundle\\":"src\/Symfony\/Bundle\/","Symfony\\Component\\":"src\/Symfony\/Component\/"},"classmap":["src\/Symfony\/Component\/Intl\/Resources\/stubs"],"exclude-from-classmap":["**\/Tests\/"]},"extra":{"branch-alias":{"dev-master":"3.3-dev"}},"require":{"doctrine\/common":"~2.4","fig\/link-util":"^1.0","php":">=5.5.9","psr\/cache":"~1.0","psr\/container":"^1.0","psr\/link":"^1.0","psr\/log":"~1.0","psr\/simple-cache":"^1.0","symfony\/polyfill-intl-icu":"~1.0","symfony\/polyfill-mbstring":"~1.0","symfony\/polyfill-php56":"~1.0","symfony\/polyfill-php70":"~1.0","symfony\/polyfill-util":"~1.0","twig\/twig":"~1.34|~2.4"},"require-dev":{"cache\/integration-tests":"dev-master","doctrine\/cache":"~1.6","doctrine\/data-fixtures":"1.0.*","doctrine\/dbal":"~2.4","doctrine\/doctrine-bundle":"~1.4","doctrine\/orm":"~2.4,>=2.4.5","egulias\/email-validator":"~1.2,>=1.2.8|~2.0","monolog\/monolog":"~1.11","ocramius\/proxy-manager":"~0.4|~1.0|~2.0","phpdocumentor\/reflection-docblock":"^3.0","predis\/predis":"~1.0","sensio\/framework-extra-bundle":"^3.0.2","symfony\/phpunit-bridge":"~3.2","symfony\/polyfill-apcu":"~1.1","symfony\/security-acl":"~2.8|~3.0"},"conflict":{"phpdocumentor\/reflection-docblock":"<3.0","phpdocumentor\/type-resolver":"<0.2.0","phpunit\/phpunit":"<4.8.35|<5.4.3,>=5.0"},"provide":{"psr\/cache-implementation":"1.0","psr\/container-implementation":"1.0","psr\/simple-cache-implementation":"1.0"},"replace":{"symfony\/asset":"self.version","symfony\/browser-kit":"self.version","symfony\/cache":"self.version","symfony\/class-loader":"self.version","symfony\/config":"self.version","symfony\/console":"self.version","symfony\/css-selector":"self.version","symfony\/dependency-injection":"self.version","symfony\/debug":"self.version","symfony\/debug-bundle":"self.version","symfony\/doctrine-bridge":"self.version","symfony\/dom-crawler":"self.version","symfony\/dotenv":"self.version","symfony\/event-dispatcher":"self.version","symfony\/expression-language":"self.version","symfony\/filesystem":"self.version","symfony\/finder":"self.version","symfony\/form":"self.version","symfony\/framework-bundle":"self.version","symfony\/http-foundation":"self.version","symfony\/http-kernel":"self.version","symfony\/inflector":"self.version","symfony\/intl":"self.version","symfony\/ldap":"self.version","symfony\/monolog-bridge":"self.version","symfony\/options-resolver":"self.version","symfony\/process":"self.version","symfony\/property-access":"self.version","symfony\/property-info":"self.version","symfony\/proxy-manager-bridge":"self.version","symfony\/routing":"self.version","symfony\/security":"self.version","symfony\/security-core":"self.version","symfony\/security-csrf":"self.version","symfony\/security-guard":"self.version","symfony\/security-http":"self.version","symfony\/security-bundle":"self.version","symfony\/serializer":"self.version","symfony\/stopwatch":"self.version","symfony\/templating":"self.version","symfony\/translation":"self.version","symfony\/twig-bridge":"self.version","symfony\/twig-bundle":"self.version","symfony\/validator":"self.version","symfony\/var-dumper":"self.version","symfony\/web-link":"self.version","symfony\/web-profiler-bundle":"self.version","symfony\/web-server-bundle":"self.version","symfony\/workflow":"self.version","symfony\/yaml":"self.version"},"uid":1480126},"v3.3.4":{"name":"symfony\/symfony","description":"The Symfony PHP framework","keywords":["framework"],"homepage":"https:\/\/symfony.com","version":"v3.3.4","version_normalized":"3.3.4.0","license":["MIT"],"authors":[{"name":"Fabien Potencier","email":"fabien@symfony.com"},{"name":"Symfony Community","homepage":"https:\/\/symfony.com\/contributors"}],"source":{"type":"git","url":"https:\/\/github.com\/symfony\/symfony.git","reference":"82f7cba3c272bcd266f2d27ad6f07832c2eb3a1c"},"dist":{"type":"zip","url":"https:\/\/api.github.com\/repos\/symfony\/symfony\/zipball\/82f7cba3c272bcd266f2d27ad6f07832c2eb3a1c","reference":"82f7cba3c272bcd266f2d27ad6f07832c2eb3a1c","shasum":""},"type":"library","time":"2017-07-05T13:28:34+00:00","autoload":{"psr-4":{"Symfony\\Bridge\\Doctrine\\":"src\/Symfony\/Bridge\/Doctrine\/","Symfony\\Bridge\\Monolog\\":"src\/Symfony\/Bridge\/Monolog\/","Symfony\\Bridge\\ProxyManager\\":"src\/Symfony\/Bridge\/ProxyManager\/","Symfony\\Bridge\\Twig\\":"src\/Symfony\/Bridge\/Twig\/","Symfony\\Bundle\\":"src\/Symfony\/Bundle\/","Symfony\\Component\\":"src\/Symfony\/Component\/"},"classmap":["src\/Symfony\/Component\/Intl\/Resources\/stubs"],"exclude-from-classmap":["**\/Tests\/"]},"extra":{"branch-alias":{"dev-master":"3.3-dev"}},"require":{"doctrine\/common":"~2.4","fig\/link-util":"^1.0","php":">=5.5.9","psr\/cache":"~1.0","psr\/container":"^1.0","psr\/link":"^1.0","psr\/log":"~1.0","psr\/simple-cache":"^1.0","symfony\/polyfill-intl-icu":"~1.0","symfony\/polyfill-mbstring":"~1.0","symfony\/polyfill-php56":"~1.0","symfony\/polyfill-php70":"~1.0","symfony\/polyfill-util":"~1.0","twig\/twig":"~1.34|~2.4"},"require-dev":{"cache\/integration-tests":"dev-master","doctrine\/cache":"~1.6","doctrine\/data-fixtures":"1.0.*","doctrine\/dbal":"~2.4","doctrine\/doctrine-bundle":"~1.4","doctrine\/orm":"~2.4,>=2.4.5","egulias\/email-validator":"~1.2,>=1.2.8|~2.0","monolog\/monolog":"~1.11","ocramius\/proxy-manager":"~0.4|~1.0|~2.0","phpdocumentor\/reflection-docblock":"^3.0","predis\/predis":"~1.0","sensio\/framework-extra-bundle":"^3.0.2","symfony\/phpunit-bridge":"~3.2","symfony\/polyfill-apcu":"~1.1","symfony\/security-acl":"~2.8|~3.0"},"conflict":{"phpdocumentor\/reflection-docblock":"<3.0","phpdocumentor\/type-resolver":"<0.2.0","phpunit\/phpunit":"<4.8.35|<5.4.3,>=5.0"},"provide":{"psr\/cache-implementation":"1.0","psr\/container-implementation":"1.0","psr\/simple-cache-implementation":"1.0"},"replace":{"symfony\/asset":"self.version","symfony\/browser-kit":"self.version","symfony\/cache":"self.version","symfony\/class-loader":"self.version","symfony\/config":"self.version","symfony\/console":"self.version","symfony\/css-selector":"self.version","symfony\/dependency-injection":"self.version","symfony\/debug":"self.version","symfony\/debug-bundle":"self.version","symfony\/doctrine-bridge":"self.version","symfony\/dom-crawler":"self.version","symfony\/dotenv":"self.version","symfony\/event-dispatcher":"self.version","symfony\/expression-language":"self.version","symfony\/filesystem":"self.version","symfony\/finder":"self.version","symfony\/form":"self.version","symfony\/framework-bundle":"self.version","symfony\/http-foundation":"self.version","symfony\/http-kernel":"self.version","symfony\/inflector":"self.version","symfony\/intl":"self.version","symfony\/ldap":"self.version","symfony\/monolog-bridge":"self.version","symfony\/options-resolver":"self.version","symfony\/process":"self.version","symfony\/property-access":"self.version","symfony\/property-info":"self.version","symfony\/proxy-manager-bridge":"self.version","symfony\/routing":"self.version","symfony\/security":"self.version","symfony\/security-core":"self.version","symfony\/security-csrf":"self.version","symfony\/security-guard":"self.version","symfony\/security-http":"self.version","symfony\/security-bundle":"self.version","symfony\/serializer":"self.version","symfony\/stopwatch":"self.version","symfony\/templating":"self.version","symfony\/translation":"self.version","symfony\/twig-bridge":"self.version","symfony\/twig-bundle":"self.version","symfony\/validator":"self.version","symfony\/var-dumper":"self.version","symfony\/web-link":"self.version","symfony\/web-profiler-bundle":"self.version","symfony\/web-server-bundle":"self.version","symfony\/workflow":"self.version","symfony\/yaml":"self.version"},"uid":1484147},"v3.3.5":{"name":"symfony\/symfony","description":"The Symfony PHP framework","keywords":["framework"],"homepage":"https:\/\/symfony.com","version":"v3.3.5","version_normalized":"3.3.5.0","license":["MIT"],"authors":[{"name":"Fabien Potencier","email":"fabien@symfony.com"},{"name":"Symfony Community","homepage":"https:\/\/symfony.com\/contributors"}],"source":{"type":"git","url":"https:\/\/github.com\/symfony\/symfony.git","reference":"b9a0d3d2393f683b28043e9dbf83b8bf6b347faa"},"dist":{"type":"zip","url":"https:\/\/api.github.com\/repos\/symfony\/symfony\/zipball\/b9a0d3d2393f683b28043e9dbf83b8bf6b347faa","reference":"b9a0d3d2393f683b28043e9dbf83b8bf6b347faa","shasum":""},"type":"library","time":"2017-07-17T19:08:46+00:00","autoload":{"psr-4":{"Symfony\\Bridge\\Doctrine\\":"src\/Symfony\/Bridge\/Doctrine\/","Symfony\\Bridge\\Monolog\\":"src\/Symfony\/Bridge\/Monolog\/","Symfony\\Bridge\\ProxyManager\\":"src\/Symfony\/Bridge\/ProxyManager\/","Symfony\\Bridge\\Twig\\":"src\/Symfony\/Bridge\/Twig\/","Symfony\\Bundle\\":"src\/Symfony\/Bundle\/","Symfony\\Component\\":"src\/Symfony\/Component\/"},"classmap":["src\/Symfony\/Component\/Intl\/Resources\/stubs"],"exclude-from-classmap":["**\/Tests\/"]},"extra":{"branch-alias":{"dev-master":"3.3-dev"}},"require":{"doctrine\/common":"~2.4","ext-xml":"*","fig\/link-util":"^1.0","php":">=5.5.9","psr\/cache":"~1.0","psr\/container":"^1.0","psr\/link":"^1.0","psr\/log":"~1.0","psr\/simple-cache":"^1.0","symfony\/polyfill-intl-icu":"~1.0","symfony\/polyfill-mbstring":"~1.0","symfony\/polyfill-php56":"~1.0","symfony\/polyfill-php70":"~1.0","symfony\/polyfill-util":"~1.0","twig\/twig":"~1.34|~2.4"},"require-dev":{"cache\/integration-tests":"dev-master","doctrine\/cache":"~1.6","doctrine\/data-fixtures":"1.0.*","doctrine\/dbal":"~2.4","doctrine\/doctrine-bundle":"~1.4","doctrine\/orm":"~2.4,>=2.4.5","egulias\/email-validator":"~1.2,>=1.2.8|~2.0","monolog\/monolog":"~1.11","ocramius\/proxy-manager":"~0.4|~1.0|~2.0","phpdocumentor\/reflection-docblock":"^3.0","predis\/predis":"~1.0","sensio\/framework-extra-bundle":"^3.0.2","symfony\/phpunit-bridge":"~3.2","symfony\/polyfill-apcu":"~1.1","symfony\/security-acl":"~2.8|~3.0"},"conflict":{"phpdocumentor\/reflection-docblock":"<3.0||>=3.2.0","phpdocumentor\/type-resolver":"<0.2.0","phpunit\/phpunit":"<4.8.35|<5.4.3,>=5.0"},"provide":{"psr\/cache-implementation":"1.0","psr\/container-implementation":"1.0","psr\/simple-cache-implementation":"1.0"},"replace":{"symfony\/asset":"self.version","symfony\/browser-kit":"self.version","symfony\/cache":"self.version","symfony\/class-loader":"self.version","symfony\/config":"self.version","symfony\/console":"self.version","symfony\/css-selector":"self.version","symfony\/dependency-injection":"self.version","symfony\/debug":"self.version","symfony\/debug-bundle":"self.version","symfony\/doctrine-bridge":"self.version","symfony\/dom-crawler":"self.version","symfony\/dotenv":"self.version","symfony\/event-dispatcher":"self.version","symfony\/expression-language":"self.version","symfony\/filesystem":"self.version","symfony\/finder":"self.version","symfony\/form":"self.version","symfony\/framework-bundle":"self.version","symfony\/http-foundation":"self.version","symfony\/http-kernel":"self.version","symfony\/inflector":"self.version","symfony\/intl":"self.version","symfony\/ldap":"self.version","symfony\/monolog-bridge":"self.version","symfony\/options-resolver":"self.version","symfony\/process":"self.version","symfony\/property-access":"self.version","symfony\/property-info":"self.version","symfony\/proxy-manager-bridge":"self.version","symfony\/routing":"self.version","symfony\/security":"self.version","symfony\/security-core":"self.version","symfony\/security-csrf":"self.version","symfony\/security-guard":"self.version","symfony\/security-http":"self.version","symfony\/security-bundle":"self.version","symfony\/serializer":"self.version","symfony\/stopwatch":"self.version","symfony\/templating":"self.version","symfony\/translation":"self.version","symfony\/twig-bridge":"self.version","symfony\/twig-bundle":"self.version","symfony\/validator":"self.version","symfony\/var-dumper":"self.version","symfony\/web-link":"self.version","symfony\/web-profiler-bundle":"self.version","symfony\/web-server-bundle":"self.version","symfony\/workflow":"self.version","symfony\/yaml":"self.version"},"uid":1504503},"v3.3.6":{"name":"symfony\/symfony","description":"The Symfony PHP framework","keywords":["framework"],"homepage":"https:\/\/symfony.com","version":"v3.3.6","version_normalized":"3.3.6.0","license":["MIT"],"authors":[{"name":"Fabien Potencier","email":"fabien@symfony.com"},{"name":"Symfony Community","homepage":"https:\/\/symfony.com\/contributors"}],"source":{"type":"git","url":"https:\/\/github.com\/symfony\/symfony.git","reference":"6f80cbd2dd89c5308b14e03d806356fac72c263e"},"dist":{"type":"zip","url":"https:\/\/api.github.com\/repos\/symfony\/symfony\/zipball\/6f80cbd2dd89c5308b14e03d806356fac72c263e","reference":"6f80cbd2dd89c5308b14e03d806356fac72c263e","shasum":""},"type":"library","time":"2017-08-01T10:26:30+00:00","autoload":{"psr-4":{"Symfony\\Bridge\\Doctrine\\":"src\/Symfony\/Bridge\/Doctrine\/","Symfony\\Bridge\\Monolog\\":"src\/Symfony\/Bridge\/Monolog\/","Symfony\\Bridge\\ProxyManager\\":"src\/Symfony\/Bridge\/ProxyManager\/","Symfony\\Bridge\\Twig\\":"src\/Symfony\/Bridge\/Twig\/","Symfony\\Bundle\\":"src\/Symfony\/Bundle\/","Symfony\\Component\\":"src\/Symfony\/Component\/"},"classmap":["src\/Symfony\/Component\/Intl\/Resources\/stubs"],"exclude-from-classmap":["**\/Tests\/"]},"extra":{"branch-alias":{"dev-master":"3.3-dev"}},"require":{"doctrine\/common":"~2.4","ext-xml":"*","fig\/link-util":"^1.0","php":">=5.5.9","psr\/cache":"~1.0","psr\/container":"^1.0","psr\/link":"^1.0","psr\/log":"~1.0","psr\/simple-cache":"^1.0","symfony\/polyfill-intl-icu":"~1.0","symfony\/polyfill-mbstring":"~1.0","symfony\/polyfill-php56":"~1.0","symfony\/polyfill-php70":"~1.0","symfony\/polyfill-util":"~1.0","twig\/twig":"~1.34|~2.4"},"require-dev":{"cache\/integration-tests":"dev-master","doctrine\/cache":"~1.6","doctrine\/data-fixtures":"1.0.*","doctrine\/dbal":"~2.4","doctrine\/doctrine-bundle":"~1.4","doctrine\/orm":"~2.4,>=2.4.5","egulias\/email-validator":"~1.2,>=1.2.8|~2.0","monolog\/monolog":"~1.11","ocramius\/proxy-manager":"~0.4|~1.0|~2.0","phpdocumentor\/reflection-docblock":"^3.0","predis\/predis":"~1.0","sensio\/framework-extra-bundle":"^3.0.2","symfony\/phpunit-bridge":"~3.2","symfony\/polyfill-apcu":"~1.1","symfony\/security-acl":"~2.8|~3.0"},"conflict":{"phpdocumentor\/reflection-docblock":"<3.0||>=3.2.0","phpdocumentor\/type-resolver":"<0.2.0","phpunit\/phpunit":"<4.8.35|<5.4.3,>=5.0"},"provide":{"psr\/cache-implementation":"1.0","psr\/container-implementation":"1.0","psr\/simple-cache-implementation":"1.0"},"replace":{"symfony\/asset":"self.version","symfony\/browser-kit":"self.version","symfony\/cache":"self.version","symfony\/class-loader":"self.version","symfony\/config":"self.version","symfony\/console":"self.version","symfony\/css-selector":"self.version","symfony\/dependency-injection":"self.version","symfony\/debug":"self.version","symfony\/debug-bundle":"self.version","symfony\/doctrine-bridge":"self.version","symfony\/dom-crawler":"self.version","symfony\/dotenv":"self.version","symfony\/event-dispatcher":"self.version","symfony\/expression-language":"self.version","symfony\/filesystem":"self.version","symfony\/finder":"self.version","symfony\/form":"self.version","symfony\/framework-bundle":"self.version","symfony\/http-foundation":"self.version","symfony\/http-kernel":"self.version","symfony\/inflector":"self.version","symfony\/intl":"self.version","symfony\/ldap":"self.version","symfony\/monolog-bridge":"self.version","symfony\/options-resolver":"self.version","symfony\/process":"self.version","symfony\/property-access":"self.version","symfony\/property-info":"self.version","symfony\/proxy-manager-bridge":"self.version","symfony\/routing":"self.version","symfony\/security":"self.version","symfony\/security-core":"self.version","symfony\/security-csrf":"self.version","symfony\/security-guard":"self.version","symfony\/security-http":"self.version","symfony\/security-bundle":"self.version","symfony\/serializer":"self.version","symfony\/stopwatch":"self.version","symfony\/templating":"self.version","symfony\/translation":"self.version","symfony\/twig-bridge":"self.version","symfony\/twig-bundle":"self.version","symfony\/validator":"self.version","symfony\/var-dumper":"self.version","symfony\/web-link":"self.version","symfony\/web-profiler-bundle":"self.version","symfony\/web-server-bundle":"self.version","symfony\/workflow":"self.version","symfony\/yaml":"self.version"},"uid":1530964},"v3.3.7":{"name":"symfony\/symfony","description":"The Symfony PHP framework","keywords":["framework"],"homepage":"https:\/\/symfony.com","version":"v3.3.7","version_normalized":"3.3.7.0","license":["MIT"],"authors":[{"name":"Fabien Potencier","email":"fabien@symfony.com"},{"name":"Symfony Community","homepage":"https:\/\/symfony.com\/contributors"}],"source":{"type":"git","url":"https:\/\/github.com\/symfony\/symfony.git","reference":"d5461f867f55e218ee712f9654d0c512a7c72771"},"dist":{"type":"zip","url":"https:\/\/api.github.com\/repos\/symfony\/symfony\/zipball\/d5461f867f55e218ee712f9654d0c512a7c72771","reference":"d5461f867f55e218ee712f9654d0c512a7c72771","shasum":""},"type":"library","time":"2017-08-28T20:18:27+00:00","autoload":{"psr-4":{"Symfony\\Bridge\\Doctrine\\":"src\/Symfony\/Bridge\/Doctrine\/","Symfony\\Bridge\\Monolog\\":"src\/Symfony\/Bridge\/Monolog\/","Symfony\\Bridge\\ProxyManager\\":"src\/Symfony\/Bridge\/ProxyManager\/","Symfony\\Bridge\\Twig\\":"src\/Symfony\/Bridge\/Twig\/","Symfony\\Bundle\\":"src\/Symfony\/Bundle\/","Symfony\\Component\\":"src\/Symfony\/Component\/"},"classmap":["src\/Symfony\/Component\/Intl\/Resources\/stubs"],"exclude-from-classmap":["**\/Tests\/"]},"extra":{"branch-alias":{"dev-master":"3.3-dev"}},"require":{"doctrine\/common":"~2.4","ext-xml":"*","fig\/link-util":"^1.0","php":"^5.5.9|>=7.0.8","psr\/cache":"~1.0","psr\/container":"^1.0","psr\/link":"^1.0","psr\/log":"~1.0","psr\/simple-cache":"^1.0","symfony\/polyfill-intl-icu":"~1.0","symfony\/polyfill-mbstring":"~1.0","symfony\/polyfill-php56":"~1.0","symfony\/polyfill-php70":"~1.0","symfony\/polyfill-util":"~1.0","twig\/twig":"~1.34|~2.4"},"require-dev":{"cache\/integration-tests":"dev-master","doctrine\/cache":"~1.6","doctrine\/data-fixtures":"1.0.*","doctrine\/dbal":"~2.4","doctrine\/doctrine-bundle":"~1.4","doctrine\/orm":"~2.4,>=2.4.5","egulias\/email-validator":"~1.2,>=1.2.8|~2.0","monolog\/monolog":"~1.11","ocramius\/proxy-manager":"~0.4|~1.0|~2.0","phpdocumentor\/reflection-docblock":"^3.0|^4.0","predis\/predis":"~1.0","sensio\/framework-extra-bundle":"^3.0.2","symfony\/phpunit-bridge":"~3.2","symfony\/polyfill-apcu":"~1.1","symfony\/security-acl":"~2.8|~3.0"},"conflict":{"phpdocumentor\/reflection-docblock":"<3.0||>=3.2.0,<3.2.2","phpdocumentor\/type-resolver":"<0.2.0","phpunit\/phpunit":"<4.8.35|<5.4.3,>=5.0"},"provide":{"psr\/cache-implementation":"1.0","psr\/container-implementation":"1.0","psr\/simple-cache-implementation":"1.0"},"replace":{"symfony\/asset":"self.version","symfony\/browser-kit":"self.version","symfony\/cache":"self.version","symfony\/class-loader":"self.version","symfony\/config":"self.version","symfony\/console":"self.version","symfony\/css-selector":"self.version","symfony\/dependency-injection":"self.version","symfony\/debug":"self.version","symfony\/debug-bundle":"self.version","symfony\/doctrine-bridge":"self.version","symfony\/dom-crawler":"self.version","symfony\/dotenv":"self.version","symfony\/event-dispatcher":"self.version","symfony\/expression-language":"self.version","symfony\/filesystem":"self.version","symfony\/finder":"self.version","symfony\/form":"self.version","symfony\/framework-bundle":"self.version","symfony\/http-foundation":"self.version","symfony\/http-kernel":"self.version","symfony\/inflector":"self.version","symfony\/intl":"self.version","symfony\/ldap":"self.version","symfony\/monolog-bridge":"self.version","symfony\/options-resolver":"self.version","symfony\/process":"self.version","symfony\/property-access":"self.version","symfony\/property-info":"self.version","symfony\/proxy-manager-bridge":"self.version","symfony\/routing":"self.version","symfony\/security":"self.version","symfony\/security-core":"self.version","symfony\/security-csrf":"self.version","symfony\/security-guard":"self.version","symfony\/security-http":"self.version","symfony\/security-bundle":"self.version","symfony\/serializer":"self.version","symfony\/stopwatch":"self.version","symfony\/templating":"self.version","symfony\/translation":"self.version","symfony\/twig-bridge":"self.version","symfony\/twig-bundle":"self.version","symfony\/validator":"self.version","symfony\/var-dumper":"self.version","symfony\/web-link":"self.version","symfony\/web-profiler-bundle":"self.version","symfony\/web-server-bundle":"self.version","symfony\/workflow":"self.version","symfony\/yaml":"self.version"},"uid":1578981},"v3.3.8":{"name":"symfony\/symfony","description":"The Symfony PHP framework","keywords":["framework"],"homepage":"https:\/\/symfony.com","version":"v3.3.8","version_normalized":"3.3.8.0","license":["MIT"],"authors":[{"name":"Fabien Potencier","email":"fabien@symfony.com"},{"name":"Symfony Community","homepage":"https:\/\/symfony.com\/contributors"}],"source":{"type":"git","url":"https:\/\/github.com\/symfony\/symfony.git","reference":"645d24a119bc7b8326bb01e7b5b696bc3be337ec"},"dist":{"type":"zip","url":"https:\/\/api.github.com\/repos\/symfony\/symfony\/zipball\/645d24a119bc7b8326bb01e7b5b696bc3be337ec","reference":"645d24a119bc7b8326bb01e7b5b696bc3be337ec","shasum":""},"type":"library","time":"2017-08-28T22:35:20+00:00","autoload":{"psr-4":{"Symfony\\Bridge\\Doctrine\\":"src\/Symfony\/Bridge\/Doctrine\/","Symfony\\Bridge\\Monolog\\":"src\/Symfony\/Bridge\/Monolog\/","Symfony\\Bridge\\ProxyManager\\":"src\/Symfony\/Bridge\/ProxyManager\/","Symfony\\Bridge\\Twig\\":"src\/Symfony\/Bridge\/Twig\/","Symfony\\Bundle\\":"src\/Symfony\/Bundle\/","Symfony\\Component\\":"src\/Symfony\/Component\/"},"classmap":["src\/Symfony\/Component\/Intl\/Resources\/stubs"],"exclude-from-classmap":["**\/Tests\/"]},"extra":{"branch-alias":{"dev-master":"3.3-dev"}},"require":{"doctrine\/common":"~2.4","ext-xml":"*","fig\/link-util":"^1.0","php":"^5.5.9|>=7.0.8","psr\/cache":"~1.0","psr\/container":"^1.0","psr\/link":"^1.0","psr\/log":"~1.0","psr\/simple-cache":"^1.0","symfony\/polyfill-intl-icu":"~1.0","symfony\/polyfill-mbstring":"~1.0","symfony\/polyfill-php56":"~1.0","symfony\/polyfill-php70":"~1.0","symfony\/polyfill-util":"~1.0","twig\/twig":"~1.34|~2.4"},"require-dev":{"cache\/integration-tests":"dev-master","doctrine\/cache":"~1.6","doctrine\/data-fixtures":"1.0.*","doctrine\/dbal":"~2.4","doctrine\/doctrine-bundle":"~1.4","doctrine\/orm":"~2.4,>=2.4.5","egulias\/email-validator":"~1.2,>=1.2.8|~2.0","monolog\/monolog":"~1.11","ocramius\/proxy-manager":"~0.4|~1.0|~2.0","phpdocumentor\/reflection-docblock":"^3.0|^4.0","predis\/predis":"~1.0","sensio\/framework-extra-bundle":"^3.0.2","symfony\/phpunit-bridge":"~3.2","symfony\/polyfill-apcu":"~1.1","symfony\/security-acl":"~2.8|~3.0"},"conflict":{"phpdocumentor\/reflection-docblock":"<3.0||>=3.2.0,<3.2.2","phpdocumentor\/type-resolver":"<0.2.0","phpunit\/phpunit":"<4.8.35|<5.4.3,>=5.0"},"provide":{"psr\/cache-implementation":"1.0","psr\/container-implementation":"1.0","psr\/simple-cache-implementation":"1.0"},"replace":{"symfony\/asset":"self.version","symfony\/browser-kit":"self.version","symfony\/cache":"self.version","symfony\/class-loader":"self.version","symfony\/config":"self.version","symfony\/console":"self.version","symfony\/css-selector":"self.version","symfony\/dependency-injection":"self.version","symfony\/debug":"self.version","symfony\/debug-bundle":"self.version","symfony\/doctrine-bridge":"self.version","symfony\/dom-crawler":"self.version","symfony\/dotenv":"self.version","symfony\/event-dispatcher":"self.version","symfony\/expression-language":"self.version","symfony\/filesystem":"self.version","symfony\/finder":"self.version","symfony\/form":"self.version","symfony\/framework-bundle":"self.version","symfony\/http-foundation":"self.version","symfony\/http-kernel":"self.version","symfony\/inflector":"self.version","symfony\/intl":"self.version","symfony\/ldap":"self.version","symfony\/monolog-bridge":"self.version","symfony\/options-resolver":"self.version","symfony\/process":"self.version","symfony\/property-access":"self.version","symfony\/property-info":"self.version","symfony\/proxy-manager-bridge":"self.version","symfony\/routing":"self.version","symfony\/security":"self.version","symfony\/security-core":"self.version","symfony\/security-csrf":"self.version","symfony\/security-guard":"self.version","symfony\/security-http":"self.version","symfony\/security-bundle":"self.version","symfony\/serializer":"self.version","symfony\/stopwatch":"self.version","symfony\/templating":"self.version","symfony\/translation":"self.version","symfony\/twig-bridge":"self.version","symfony\/twig-bundle":"self.version","symfony\/validator":"self.version","symfony\/var-dumper":"self.version","symfony\/web-link":"self.version","symfony\/web-profiler-bundle":"self.version","symfony\/web-server-bundle":"self.version","symfony\/workflow":"self.version","symfony\/yaml":"self.version"},"uid":1579198}},"symfony\/web-server-bundle":{"3.3.x-dev":{"name":"symfony\/web-server-bundle","description":"Symfony WebServerBundle","keywords":[],"homepage":"https:\/\/symfony.com","version":"3.3.x-dev","version_normalized":"3.3.9999999.9999999-dev","license":["MIT"],"authors":[{"name":"Fabien Potencier","email":"fabien@symfony.com"},{"name":"Symfony Community","homepage":"https:\/\/symfony.com\/contributors"}],"source":{"type":"git","url":"https:\/\/github.com\/symfony\/web-server-bundle.git","reference":"b2508667fd9d468135f054c5afc59bc8a5ab7bc7"},"dist":{"type":"zip","url":"https:\/\/api.github.com\/repos\/symfony\/web-server-bundle\/zipball\/b2508667fd9d468135f054c5afc59bc8a5ab7bc7","reference":"b2508667fd9d468135f054c5afc59bc8a5ab7bc7","shasum":""},"type":"symfony-bundle","time":"2017-08-22T13:33:42+00:00","autoload":{"psr-4":{"Symfony\\Bundle\\WebServerBundle\\":""},"exclude-from-classmap":["\/Tests\/"]},"extra":{"branch-alias":{"dev-master":"3.3-dev"}},"require":{"symfony\/http-kernel":"~3.3","symfony\/console":"~3.3","symfony\/process":"~3.3","php":"^5.5.9|>=7.0.8"},"conflict":{"symfony\/dependency-injection":"<3.3"},"uid":1400311},"3.4.x-dev":{"name":"symfony\/web-server-bundle","description":"Symfony WebServerBundle","keywords":[],"homepage":"https:\/\/symfony.com","version":"3.4.x-dev","version_normalized":"3.4.9999999.9999999-dev","license":["MIT"],"authors":[{"name":"Fabien Potencier","email":"fabien@symfony.com"},{"name":"Symfony Community","homepage":"https:\/\/symfony.com\/contributors"}],"source":{"type":"git","url":"https:\/\/github.com\/symfony\/web-server-bundle.git","reference":"e08b43f7c1a6a310b4d04bf1c0966ad7d33174be"},"dist":{"type":"zip","url":"https:\/\/api.github.com\/repos\/symfony\/web-server-bundle\/zipball\/e08b43f7c1a6a310b4d04bf1c0966ad7d33174be","reference":"e08b43f7c1a6a310b4d04bf1c0966ad7d33174be","shasum":""},"type":"symfony-bundle","time":"2017-08-22T16:06:26+00:00","autoload":{"psr-4":{"Symfony\\Bundle\\WebServerBundle\\":""},"exclude-from-classmap":["\/Tests\/"]},"extra":{"branch-alias":{"dev-master":"3.4-dev"}},"require":{"symfony\/http-kernel":"~3.3|~4.0","symfony\/process":"~3.3|~4.0","symfony\/console":"~3.3|~4.0","php":"^5.5.9|>=7.0.8"},"conflict":{"symfony\/dependency-injection":"<3.3"},"uid":1400358},"dev-master":{"name":"symfony\/web-server-bundle","description":"Symfony WebServerBundle","keywords":[],"homepage":"https:\/\/symfony.com","version":"dev-master","version_normalized":"9999999-dev","license":["MIT"],"authors":[{"name":"Fabien Potencier","email":"fabien@symfony.com"},{"name":"Symfony Community","homepage":"https:\/\/symfony.com\/contributors"}],"source":{"type":"git","url":"https:\/\/github.com\/symfony\/web-server-bundle.git","reference":"97197d88c628dfc87a9edd63eb64846efdcb6332"},"dist":{"type":"zip","url":"https:\/\/api.github.com\/repos\/symfony\/web-server-bundle\/zipball\/97197d88c628dfc87a9edd63eb64846efdcb6332","reference":"97197d88c628dfc87a9edd63eb64846efdcb6332","shasum":""},"type":"symfony-bundle","time":"2017-08-22T16:07:47+00:00","autoload":{"psr-4":{"Symfony\\Bundle\\WebServerBundle\\":""},"exclude-from-classmap":["\/Tests\/"]},"extra":{"branch-alias":{"dev-master":"4.0-dev"}},"require":{"php":"^7.1.3","symfony\/console":"~3.4|~4.0","symfony\/http-kernel":"~3.4|~4.0","symfony\/process":"~3.4|~4.0"},"conflict":{"symfony\/dependency-injection":"<3.4"},"uid":1159926},"v3.3.0":{"name":"symfony\/web-server-bundle","description":"Symfony WebServerBundle","keywords":[],"homepage":"https:\/\/symfony.com","version":"v3.3.0","version_normalized":"3.3.0.0","license":["MIT"],"authors":[{"name":"Fabien Potencier","email":"fabien@symfony.com"},{"name":"Symfony Community","homepage":"https:\/\/symfony.com\/contributors"}],"source":{"type":"git","url":"https:\/\/github.com\/symfony\/web-server-bundle.git","reference":"8d819587480d1d577a4702b1baccfea0bad3cb9b"},"dist":{"type":"zip","url":"https:\/\/api.github.com\/repos\/symfony\/web-server-bundle\/zipball\/8d819587480d1d577a4702b1baccfea0bad3cb9b","reference":"8d819587480d1d577a4702b1baccfea0bad3cb9b","shasum":""},"type":"symfony-bundle","time":"2017-05-23T09:11:47+00:00","autoload":{"psr-4":{"Symfony\\Bundle\\WebServerBundle\\":""},"exclude-from-classmap":["\/Tests\/"]},"extra":{"branch-alias":{"dev-master":"3.3-dev"}},"require":{"php":">=5.5.9","symfony\/console":"~2.8.8|~3.0.8|~3.1.2|~3.2","symfony\/http-kernel":"~3.3","symfony\/process":"~2.8|~3.0"},"conflict":{"symfony\/dependency-injection":"<3.3"},"uid":1417877},"v3.3.0-BETA1":{"name":"symfony\/web-server-bundle","description":"Symfony WebServerBundle","keywords":[],"homepage":"https:\/\/symfony.com","version":"v3.3.0-BETA1","version_normalized":"3.3.0.0-beta1","license":["MIT"],"authors":[{"name":"Fabien Potencier","email":"fabien@symfony.com"},{"name":"Symfony Community","homepage":"https:\/\/symfony.com\/contributors"}],"source":{"type":"git","url":"https:\/\/github.com\/symfony\/web-server-bundle.git","reference":"7c04e418d04b091b73ad940e40ad5fa3602d772f"},"dist":{"type":"zip","url":"https:\/\/api.github.com\/repos\/symfony\/web-server-bundle\/zipball\/7c04e418d04b091b73ad940e40ad5fa3602d772f","reference":"7c04e418d04b091b73ad940e40ad5fa3602d772f","shasum":""},"type":"symfony-bundle","time":"2017-04-12T14:15:58+00:00","autoload":{"psr-4":{"Symfony\\Bundle\\WebServerBundle\\":""},"exclude-from-classmap":["\/Tests\/"]},"extra":{"branch-alias":{"dev-master":"3.3-dev"}},"require":{"php":">=5.5.9","symfony\/console":"~2.8.8|~3.0.8|~3.1.2|~3.2","symfony\/process":"~2.8|~3.0"},"uid":1369983},"v3.3.0-RC1":{"name":"symfony\/web-server-bundle","description":"Symfony WebServerBundle","keywords":[],"homepage":"https:\/\/symfony.com","version":"v3.3.0-RC1","version_normalized":"3.3.0.0-RC1","license":["MIT"],"authors":[{"name":"Fabien Potencier","email":"fabien@symfony.com"},{"name":"Symfony Community","homepage":"https:\/\/symfony.com\/contributors"}],"source":{"type":"git","url":"https:\/\/github.com\/symfony\/web-server-bundle.git","reference":"e8c4193879e0a53cbb8f93e2f7cad6a4ce0ed400"},"dist":{"type":"zip","url":"https:\/\/api.github.com\/repos\/symfony\/web-server-bundle\/zipball\/e8c4193879e0a53cbb8f93e2f7cad6a4ce0ed400","reference":"e8c4193879e0a53cbb8f93e2f7cad6a4ce0ed400","shasum":""},"type":"symfony-bundle","time":"2017-05-12T10:42:32+00:00","autoload":{"psr-4":{"Symfony\\Bundle\\WebServerBundle\\":""},"exclude-from-classmap":["\/Tests\/"]},"extra":{"branch-alias":{"dev-master":"3.3-dev"}},"require":{"php":">=5.5.9","symfony\/console":"~2.8.8|~3.0.8|~3.1.2|~3.2","symfony\/http-kernel":"~2.8|~3.0","symfony\/process":"~2.8|~3.0"},"conflict":{"symfony\/dependency-injection":"<3.3"},"uid":1400492},"v3.3.1":{"name":"symfony\/web-server-bundle","description":"Symfony WebServerBundle","keywords":[],"homepage":"https:\/\/symfony.com","version":"v3.3.1","version_normalized":"3.3.1.0","license":["MIT"],"authors":[{"name":"Fabien Potencier","email":"fabien@symfony.com"},{"name":"Symfony Community","homepage":"https:\/\/symfony.com\/contributors"}],"source":{"type":"git","url":"https:\/\/github.com\/symfony\/web-server-bundle.git","reference":"8d819587480d1d577a4702b1baccfea0bad3cb9b"},"dist":{"type":"zip","url":"https:\/\/api.github.com\/repos\/symfony\/web-server-bundle\/zipball\/8d819587480d1d577a4702b1baccfea0bad3cb9b","reference":"8d819587480d1d577a4702b1baccfea0bad3cb9b","shasum":""},"type":"symfony-bundle","time":"2017-05-23T09:11:47+00:00","autoload":{"psr-4":{"Symfony\\Bundle\\WebServerBundle\\":""},"exclude-from-classmap":["\/Tests\/"]},"extra":{"branch-alias":{"dev-master":"3.3-dev"}},"require":{"php":">=5.5.9","symfony\/console":"~2.8.8|~3.0.8|~3.1.2|~3.2","symfony\/http-kernel":"~3.3","symfony\/process":"~2.8|~3.0"},"conflict":{"symfony\/dependency-injection":"<3.3"},"uid":1428903},"v3.3.2":{"name":"symfony\/web-server-bundle","description":"Symfony WebServerBundle","keywords":[],"homepage":"https:\/\/symfony.com","version":"v3.3.2","version_normalized":"3.3.2.0","license":["MIT"],"authors":[{"name":"Fabien Potencier","email":"fabien@symfony.com"},{"name":"Symfony Community","homepage":"https:\/\/symfony.com\/contributors"}],"source":{"type":"git","url":"https:\/\/github.com\/symfony\/web-server-bundle.git","reference":"8d819587480d1d577a4702b1baccfea0bad3cb9b"},"dist":{"type":"zip","url":"https:\/\/api.github.com\/repos\/symfony\/web-server-bundle\/zipball\/8d819587480d1d577a4702b1baccfea0bad3cb9b","reference":"8d819587480d1d577a4702b1baccfea0bad3cb9b","shasum":""},"type":"symfony-bundle","time":"2017-05-23T09:11:47+00:00","autoload":{"psr-4":{"Symfony\\Bundle\\WebServerBundle\\":""},"exclude-from-classmap":["\/Tests\/"]},"extra":{"branch-alias":{"dev-master":"3.3-dev"}},"require":{"php":">=5.5.9","symfony\/console":"~2.8.8|~3.0.8|~3.1.2|~3.2","symfony\/http-kernel":"~3.3","symfony\/process":"~2.8|~3.0"},"conflict":{"symfony\/dependency-injection":"<3.3"},"uid":1429579},"v3.3.3":{"name":"symfony\/web-server-bundle","description":"Symfony WebServerBundle","keywords":[],"homepage":"https:\/\/symfony.com","version":"v3.3.3","version_normalized":"3.3.3.0","license":["MIT"],"authors":[{"name":"Fabien Potencier","email":"fabien@symfony.com"},{"name":"Symfony Community","homepage":"https:\/\/symfony.com\/contributors"}],"source":{"type":"git","url":"https:\/\/github.com\/symfony\/web-server-bundle.git","reference":"29efd11460bc27c28d0ba89f41b39ef0129f780f"},"dist":{"type":"zip","url":"https:\/\/api.github.com\/repos\/symfony\/web-server-bundle\/zipball\/29efd11460bc27c28d0ba89f41b39ef0129f780f","reference":"29efd11460bc27c28d0ba89f41b39ef0129f780f","shasum":""},"type":"symfony-bundle","time":"2017-06-16T13:28:11+00:00","autoload":{"psr-4":{"Symfony\\Bundle\\WebServerBundle\\":""},"exclude-from-classmap":["\/Tests\/"]},"extra":{"branch-alias":{"dev-master":"3.3-dev"}},"require":{"php":">=5.5.9","symfony\/console":"~2.8.8|~3.0.8|~3.1.2|~3.2","symfony\/http-kernel":"~3.3","symfony\/process":"~2.8|~3.0"},"conflict":{"symfony\/dependency-injection":"<3.3"},"uid":1480167},"v3.3.4":{"name":"symfony\/web-server-bundle","description":"Symfony WebServerBundle","keywords":[],"homepage":"https:\/\/symfony.com","version":"v3.3.4","version_normalized":"3.3.4.0","license":["MIT"],"authors":[{"name":"Fabien Potencier","email":"fabien@symfony.com"},{"name":"Symfony Community","homepage":"https:\/\/symfony.com\/contributors"}],"source":{"type":"git","url":"https:\/\/github.com\/symfony\/web-server-bundle.git","reference":"29efd11460bc27c28d0ba89f41b39ef0129f780f"},"dist":{"type":"zip","url":"https:\/\/api.github.com\/repos\/symfony\/web-server-bundle\/zipball\/29efd11460bc27c28d0ba89f41b39ef0129f780f","reference":"29efd11460bc27c28d0ba89f41b39ef0129f780f","shasum":""},"type":"symfony-bundle","time":"2017-06-16T13:28:11+00:00","autoload":{"psr-4":{"Symfony\\Bundle\\WebServerBundle\\":""},"exclude-from-classmap":["\/Tests\/"]},"extra":{"branch-alias":{"dev-master":"3.3-dev"}},"require":{"php":">=5.5.9","symfony\/console":"~2.8.8|~3.0.8|~3.1.2|~3.2","symfony\/http-kernel":"~3.3","symfony\/process":"~2.8|~3.0"},"conflict":{"symfony\/dependency-injection":"<3.3"},"uid":1484160},"v3.3.5":{"name":"symfony\/web-server-bundle","description":"Symfony WebServerBundle","keywords":[],"homepage":"https:\/\/symfony.com","version":"v3.3.5","version_normalized":"3.3.5.0","license":["MIT"],"authors":[{"name":"Fabien Potencier","email":"fabien@symfony.com"},{"name":"Symfony Community","homepage":"https:\/\/symfony.com\/contributors"}],"source":{"type":"git","url":"https:\/\/github.com\/symfony\/web-server-bundle.git","reference":"3f908d68e47d8ea286041ebb15ff8c626cafa46a"},"dist":{"type":"zip","url":"https:\/\/api.github.com\/repos\/symfony\/web-server-bundle\/zipball\/3f908d68e47d8ea286041ebb15ff8c626cafa46a","reference":"3f908d68e47d8ea286041ebb15ff8c626cafa46a","shasum":""},"type":"symfony-bundle","time":"2017-07-16T12:41:56+00:00","autoload":{"psr-4":{"Symfony\\Bundle\\WebServerBundle\\":""},"exclude-from-classmap":["\/Tests\/"]},"extra":{"branch-alias":{"dev-master":"3.3-dev"}},"require":{"php":">=5.5.9","symfony\/console":"~2.8.8|~3.0.8|~3.1.2|~3.2","symfony\/http-kernel":"~3.3","symfony\/process":"~2.8|~3.0"},"conflict":{"symfony\/dependency-injection":"<3.3"},"uid":1504520},"v3.3.6":{"name":"symfony\/web-server-bundle","description":"Symfony WebServerBundle","keywords":[],"homepage":"https:\/\/symfony.com","version":"v3.3.6","version_normalized":"3.3.6.0","license":["MIT"],"authors":[{"name":"Fabien Potencier","email":"fabien@symfony.com"},{"name":"Symfony Community","homepage":"https:\/\/symfony.com\/contributors"}],"source":{"type":"git","url":"https:\/\/github.com\/symfony\/web-server-bundle.git","reference":"5c49ef72162feafbbf55e94bef6f621f4b8437e8"},"dist":{"type":"zip","url":"https:\/\/api.github.com\/repos\/symfony\/web-server-bundle\/zipball\/5c49ef72162feafbbf55e94bef6f621f4b8437e8","reference":"5c49ef72162feafbbf55e94bef6f621f4b8437e8","shasum":""},"type":"symfony-bundle","time":"2017-07-26T16:08:22+00:00","autoload":{"psr-4":{"Symfony\\Bundle\\WebServerBundle\\":""},"exclude-from-classmap":["\/Tests\/"]},"extra":{"branch-alias":{"dev-master":"3.3-dev"}},"require":{"php":">=5.5.9","symfony\/console":"~3.3","symfony\/http-kernel":"~3.3","symfony\/process":"~3.3"},"conflict":{"symfony\/dependency-injection":"<3.3"},"uid":1530969},"v3.3.7":{"name":"symfony\/web-server-bundle","description":"Symfony WebServerBundle","keywords":[],"homepage":"https:\/\/symfony.com","version":"v3.3.7","version_normalized":"3.3.7.0","license":["MIT"],"authors":[{"name":"Fabien Potencier","email":"fabien@symfony.com"},{"name":"Symfony Community","homepage":"https:\/\/symfony.com\/contributors"}],"source":{"type":"git","url":"https:\/\/github.com\/symfony\/web-server-bundle.git","reference":"b2508667fd9d468135f054c5afc59bc8a5ab7bc7"},"dist":{"type":"zip","url":"https:\/\/api.github.com\/repos\/symfony\/web-server-bundle\/zipball\/b2508667fd9d468135f054c5afc59bc8a5ab7bc7","reference":"b2508667fd9d468135f054c5afc59bc8a5ab7bc7","shasum":""},"type":"symfony-bundle","time":"2017-08-22T13:33:42+00:00","autoload":{"psr-4":{"Symfony\\Bundle\\WebServerBundle\\":""},"exclude-from-classmap":["\/Tests\/"]},"extra":{"branch-alias":{"dev-master":"3.3-dev"}},"require":{"php":"^5.5.9|>=7.0.8","symfony\/console":"~3.3","symfony\/http-kernel":"~3.3","symfony\/process":"~3.3"},"conflict":{"symfony\/dependency-injection":"<3.3"},"uid":1578991},"v3.3.8":{"name":"symfony\/web-server-bundle","description":"Symfony WebServerBundle","keywords":[],"homepage":"https:\/\/symfony.com","version":"v3.3.8","version_normalized":"3.3.8.0","license":["MIT"],"authors":[{"name":"Fabien Potencier","email":"fabien@symfony.com"},{"name":"Symfony Community","homepage":"https:\/\/symfony.com\/contributors"}],"source":{"type":"git","url":"https:\/\/github.com\/symfony\/web-server-bundle.git","reference":"b2508667fd9d468135f054c5afc59bc8a5ab7bc7"},"dist":{"type":"zip","url":"https:\/\/api.github.com\/repos\/symfony\/web-server-bundle\/zipball\/b2508667fd9d468135f054c5afc59bc8a5ab7bc7","reference":"b2508667fd9d468135f054c5afc59bc8a5ab7bc7","shasum":""},"type":"symfony-bundle","time":"2017-08-22T13:33:42+00:00","autoload":{"psr-4":{"Symfony\\Bundle\\WebServerBundle\\":""},"exclude-from-classmap":["\/Tests\/"]},"extra":{"branch-alias":{"dev-master":"3.3-dev"}},"require":{"php":"^5.5.9|>=7.0.8","symfony\/console":"~3.3","symfony\/http-kernel":"~3.3","symfony\/process":"~3.3"},"conflict":{"symfony\/dependency-injection":"<3.3"},"uid":1579209}}}}